editglancer/__init__.py
editglancer/editglancer.py
editglancer/utils.py
editglancer-0.1.3.dist-info/LICENSE
editglancer-0.1.3.dist-info/METADATA
editglancer-0.1.3.dist-info/WHEEL
editglancer-0.1.3.dist-info/RECORD
