Metadata-Version: 2.1
Name: editglancer
Version: 0.1.3
Summary: Tools for visualizing neuron edits in neuroglancer from Python scripts.
Home-page: https://github.com/CAVEconnectome/editglancer
License: MIT
Author: Ben Pedigo
Author-email: ben.pedigo@alleninstitute.org
Requires-Python: >=3.8.0,<3.12.0
Classifier: Development Status :: 2 - Pre-Alpha
Classifier: Intended Audience :: Developers
Classifier: License :: OSI Approved :: MIT License
Classifier: Natural Language :: English
Classifier: Programming Language :: Python :: 3
Classifier: Programming Language :: Python :: 3.8
Classifier: Programming Language :: Python :: 3.9
Classifier: Programming Language :: Python :: 3.10
Classifier: Programming Language :: Python :: 3.11
Requires-Dist: beartype (>=0.16.4,<0.17.0)
Requires-Dist: nglui (>=3.0.2,<4.0.0)
Requires-Dist: types-pytz (>=2024.1.0.20240203,<2025.0.0.0)
